{
  "id": "LOV-2026-02-13-6",
  "source_dataset": "gjeldende-lover",
  "archive_filename": "gjeldende-lover.tar.bz2",
  "archive_last_modified": "2026-05-02T01:31:00Z",
  "document_type": "lov",
  "title": "Lov om endringer i opplæringslova (rett til 12 timer gratis skolefritidsordning i uken for elever på 1. til 3. trinn)",
  "short_title": "Endringslov til opplæringslova",
  "department": "Kunnskapsdepartementet",
  "legal_area": "Skoler, universiteter og forskning > Skoler. Privatskoler",
  "date_in_force": "2026-08-01",
  "lovdata_refid": "lov/2026-02-13-6",
  "source_url": "https://lovdata.no/dokument/NL/lov/2026-02-13-6",
  "raw_xml_sha256": "841dacfb127872fb7a72c529c92dc118627ce8be4e90f980a8f6d3fc8589cdb5",
  "sections": [
    {
      "section_id": "dokument",
      "provision_ref": "document",
      "heading": "Lov om endringer i opplæringslova (rett til 12 timer gratis skolefritidsordning i uken for elever på 1. til 3. trinn)",
      "path": [],
      "text": "Lov om endringer i opplæringslova (rett til 12 timer gratis skolefritidsordning i uken for elever på 1. til 3. trinn)Endringer i følgende lov:Lov 9. juni 2023 nr. 30 om grunnskoleopplæringa og den vidaregåande opplæringa (opplæringslova).II lov 9. juni 2023 nr. 30 om grunnskoleopplæringa og den vidaregåande opplæringa gjøres følgende endringer:§ 4-5 andre ledd skal lyde:Elevar på 1. til 3. trinn har rett til 12 timar gratis skolefritidsordning per veke.Nåværende andre til femte ledd blir tredje til sjette ledd.Nåværende sjette ledd blir nytt syvende ledd og skal lyde:Departementet kan gi forskrift om retten til skolefritidsordning, gratis skolefritidsordning, moderasjonsordningar og innhald i og oppgåver for skolefritidsordninga.IILoven gjelder fra den tiden1 Kongen fastsetter.1 Fra 1. august 2026 iflg. res. 13 feb 2026 nr. 197.",
      "xml_path": "main#dokument"
    }
  ]
}
