{
  "id": "FOR-2003-07-09-945",
  "source_dataset": "gjeldende-sentrale-forskrifter",
  "archive_filename": "gjeldende-sentrale-forskrifter.tar.bz2",
  "archive_last_modified": "2026-05-05T01:32:00Z",
  "document_type": "forskrift",
  "title": "Forskrift om særskilte beskyttelsestiltak ved innførsel av præriehunder fra USA, samt ikke-domestiserte gnagere og ekorn fra subsahariske land i Afrika i forbindelse med utbrudd av apekoppevirus",
  "short_title": "Forskrift om tiltak mot apekoppvirus",
  "department": "Landbruks- og matdepartementet",
  "date_in_force": "2003-07-09",
  "last_change_in_force": "2016-06-01",
  "last_changed_by": "forskrift/2016-05-19-543 fra 2016-06-01",
  "lovdata_refid": "forskrift/2003-07-09-945",
  "source_url": "https://lovdata.no/dokument/SF/forskrift/2003-07-09-945",
  "raw_xml_sha256": "6092479193af1b9139f9dcae5dc46366dd4793d1041b1111f55271910f6421e8",
  "sections": [
    {
      "section_id": "paragraf-1",
      "provision_ref": "§ 1",
      "heading": "Formål og virkeområde",
      "path": [],
      "text": "Formålet med denne forskrift er å forebygge spredning av apekoppevirus i forbindelse med innførsel av præriehunder fra eller med opprinnelse i USA, samt ikke-domestiserte gnagere og ekorn fra subsahariske land i Afrika.",
      "xml_path": "article#paragraf-1"
    },
    {
      "section_id": "paragraf-2",
      "provision_ref": "§ 2",
      "heading": "Definisjoner",
      "path": [],
      "text": "Med subsahariske land forstås afrikansk territorium mellom breddegrad 15° N og 15° S.\nMed et domestisert dyr forstås et dyr som er tilpasset å skulle leve i et menneskeskapt miljø.",
      "xml_path": "article#paragraf-2"
    },
    {
      "section_id": "paragraf-3",
      "provision_ref": "§ 3",
      "heading": "Forbud",
      "path": [],
      "text": "Det er forbudt å innføre præriehunder fra eller med opprinnelse i USA, samt ikke-domestiserte gnagere og ekorn fra subsahariske land i Afrika.",
      "xml_path": "article#paragraf-3"
    },
    {
      "section_id": "paragraf-4",
      "provision_ref": "§ 4",
      "heading": "Dispensasjon",
      "path": [],
      "text": "Mattilsynet kan dispensere fra forbudet i § 3 i denne forskrift, dersom dyrene kommer fra og skal til godkjente organer, institutter eller stasjoner som definert i forskrift 20. februar 2004 nr. 464 om dyrehelsemessige betingelser for import og eksport av levende dyr, sæd, egg og embryo § 3 nr. 1.",
      "xml_path": "article#paragraf-4"
    },
    {
      "section_id": "paragraf-5",
      "provision_ref": "§ 5",
      "heading": "Straff",
      "path": [],
      "text": "Forsettlig eller uaktsom overtredelse av denne forskriften eller bestemmelser og vedtak gitt i medhold av den, er straffbart i henhold til matloven § 28.",
      "xml_path": "article#paragraf-5"
    },
    {
      "section_id": "paragraf-6",
      "provision_ref": "§ 6",
      "heading": "Ikrafttredelse",
      "path": [],
      "text": "Denne forskrift trer i kraft straks.",
      "xml_path": "article#paragraf-6"
    }
  ]
}
